clease_gui/__init__.py
clease_gui/_version.txt
clease_gui/app_data.py
clease_gui/base_dashboard.py
clease_gui/colors.py
clease_gui/dashboard_interface.py
clease_gui/db_viewer.py
clease_gui/event_context.py
clease_gui/logging_widget.py
clease_gui/main.py
clease_gui/main_dashboard.py
clease_gui/singleton.py
clease_gui/status_bar.py
clease_gui/style_mixin.py
clease_gui/timing.py
clease_gui/utils.py
clease_gui/version.py
clease_gui/widget_collection.py
clease_gui/assets/__init__.py
clease_gui/assets/clease_logo.png
clease_gui/assets/default_notebook.ipynb
clease_gui/calculate/__init__.py
clease_gui/calculate/calculate.py
clease_gui/calculate/emt_calculator.py
clease_gui/cli/__init__.py
clease_gui/cli/launch_notebook.py
clease_gui/cli/main_cli.py
clease_gui/cli/notebook.py
clease_gui/fitting/__init__.py
clease_gui/fitting/eci_fit.py
clease_gui/fitting/fitting_main.py
clease_gui/fitting/fitting_widgets.py
clease_gui/fitting/plots_dashboard.py
clease_gui/montecarlo/__init__.py
clease_gui/montecarlo/canonical_mc.py
clease_gui/montecarlo/mc_main.py
clease_gui/montecarlo/mc_nglviewer.py
clease_gui/montecarlo/mc_run_dashboard.py
clease_gui/montecarlo/plot_mc_page.py
clease_gui/montecarlo/view_mc_dashboard.py
clease_gui/new_structures/__init__.py
clease_gui/new_structures/general_new_struct_settings.py
clease_gui/new_structures/new_structures.py
clease_gui/new_structures/structure_gen.py
clease_gui/new_structures/structure_gen_kwarg_widgets.py
clease_gui/settings_maker/__init__.py
clease_gui/settings_maker/ce_settings.py
clease_gui/settings_maker/cluster_dashboard.py
clease_gui/settings_maker/concentration.py
clease_gui/settings_maker/settings_buttons.py
clease_gui/settings_maker/settings_maker.py
clease_gui/settings_maker/structure_settings.py
clease_gui/supercell/__init__.py
clease_gui/supercell/supercell_dashboard.py
clease_gui-0.2.2.dist-info/LICENSE.md
clease_gui-0.2.2.dist-info/METADATA
clease_gui-0.2.2.dist-info/WHEEL
clease_gui-0.2.2.dist-info/entry_points.txt
clease_gui-0.2.2.dist-info/top_level.txt
clease_gui-0.2.2.dist-info/RECORD
