Metadata-Version: 2.1
Name: clease-gui
Version: 0.2.2
Summary: GUI for CLEASE
Home-page: https://gitlab.com/computationalmaterials/clease-gui
Author: Alexander S. Tygesen
Author-email: alexty@dtu.dk
License: MPL-2.0
Project-URL: Documentation, https://clease-gui.readthedocs.io
Project-URL: Source, https://gitlab.com/computationalmaterials/clease-gui
Keywords: Cluster Expansion,Monte Carlo,Computational materials,Materials research,GUI,Graphical User Interface,CLEASE
Classifier: Development Status :: 4 - Beta
Classifier: Operating System :: OS Independent
Classifier: License :: OSI Approved :: Mozilla Public License 2.0 (MPL 2.0)
Classifier: Framework :: Jupyter
Classifier: Programming Language :: Python :: 3.7
Classifier: Programming Language :: Python :: 3.8
Classifier: Programming Language :: Python :: 3.9
Classifier: Programming Language :: Python :: 3.10
Requires-Python: >=3.7
License-File: LICENSE.md
Requires-Dist: ipython
Requires-Dist: jupyterlab
Requires-Dist: ipywidgets
Requires-Dist: clease (>=1.0.0)
Requires-Dist: pandas
Requires-Dist: numpy
Requires-Dist: matplotlib
Requires-Dist: click (>=8.0.0)
Requires-Dist: ase
Requires-Dist: nglview
Requires-Dist: packaging
Requires-Dist: attrs (>=21.4.0)
Provides-Extra: all
Requires-Dist: pytest-mock ; extra == 'all'
Requires-Dist: sphinx ; extra == 'all'
Requires-Dist: twine ; extra == 'all'
Requires-Dist: pylint ; extra == 'all'
Requires-Dist: build ; extra == 'all'
Requires-Dist: tox ; extra == 'all'
Requires-Dist: black[jupyter] ; extra == 'all'
Requires-Dist: pyclean (>=2.0.0) ; extra == 'all'
Requires-Dist: pre-commit ; extra == 'all'
Requires-Dist: sphinx-rtd-theme ; extra == 'all'
Requires-Dist: pytest (>=4) ; extra == 'all'
Requires-Dist: flake8 ; extra == 'all'
Provides-Extra: dev
Requires-Dist: pre-commit ; extra == 'dev'
Requires-Dist: black[jupyter] ; extra == 'dev'
Requires-Dist: flake8 ; extra == 'dev'
Requires-Dist: pylint ; extra == 'dev'
Requires-Dist: tox ; extra == 'dev'
Provides-Extra: doc
Requires-Dist: sphinx ; extra == 'doc'
Requires-Dist: sphinx-rtd-theme ; extra == 'doc'
Provides-Extra: publish
Requires-Dist: pyclean (>=2.0.0) ; extra == 'publish'
Requires-Dist: twine ; extra == 'publish'
Requires-Dist: build ; extra == 'publish'
Provides-Extra: test
Requires-Dist: pytest (>=4) ; extra == 'test'
Requires-Dist: pytest-mock ; extra == 'test'
